{
    "chartData": {
        "datasets": [
            {
                "data": [
                    {
                        "x": 37.935777833335436,
                        "y": 23.967741750737503,
                        "l": "マルリナの明日／殺人者マルリナ"
                    },
                    {
                        "x": 28.985417073447458,
                        "y": 30.67861218033742,
                        "l": "こどもしょくどう"
                    },
                    {
                        "x": 39.166417706928144,
                        "y": 22.52956298977263,
                        "l": "人生フルーツ"
                    },
                    {
                        "x": 31.77444653045627,
                        "y": 22.206165915468766,
                        "l": "Girl／ガール"
                    },
                    {
                        "x": 27.929984183599004,
                        "y": 31.512078042746126,
                        "l": "ザ・ナンバー"
                    },
                    {
                        "x": 37.67925798749343,
                        "y": 34.51713081524747,
                        "l": "殺し屋"
                    },
                    {
                        "x": 30.149725543558738,
                        "y": 25.062229798618596,
                        "l": "ブラック・クランズマン"
                    },
                    {
                        "x": 29.698642854008003,
                        "y": 28.980932504927488,
                        "l": "破天荒ボクサー"
                    },
                    {
                        "x": 35.41684401377096,
                        "y": 33.24224887121751,
                        "l": "モーターギャング"
                    },
                    {
                        "x": 37.63507909604071,
                        "y": 25.86793165834524,
                        "l": "トラさん～僕が猫になったワケ～"
                    },
                    {
                        "x": 24.268984934823408,
                        "y": 36.97032441588475,
                        "l": "ワイルドツアー"
                    },
                    {
                        "x": 20.62206858590011,
                        "y": 28.17481666048021,
                        "l": "ナイトクルージング"
                    },
                    {
                        "x": 17.957688648558978,
                        "y": 38.72311603315948,
                        "l": "PARKS パークス"
                    },
                    {
                        "x": 35.095694928732634,
                        "y": 29.99231285758195,
                        "l": "ルートヴィヒ"
                    },
                    {
                        "x": 28.668146182062962,
                        "y": 29.793353409542622,
                        "l": "ミュウツーの逆襲 EVOLUTION"
                    },
                    {
                        "x": 27.435420428470355,
                        "y": 28.53051573463304,
                        "l": "パラレルワールド・ラブストーリー"
                    },
                    {
                        "x": 33.90168480988412,
                        "y": 28.664940788173382,
                        "l": "アクアマン"
                    },
                    {
                        "x": 34.29303719939107,
                        "y": 25.27492660903863,
                        "l": "ガラスの城の約束"
                    },
                    {
                        "x": 26.475842613530997,
                        "y": 30.88219262343753,
                        "l": "広告会社、男子寮のおかずくん"
                    },
                    {
                        "x": 32.54764399252075,
                        "y": 25.986159731694148,
                        "l": "ビッグ・シック ぼくたちの大いなる目ざめ"
                    },
                    {
                        "x": 30.001322105312664,
                        "y": 29.63909321792368,
                        "l": "居眠り磐音"
                    },
                    {
                        "x": 28.565151344621313,
                        "y": 40.658179066333304,
                        "l": "スパイダーマン：ファー・フロム・ホーム"
                    },
                    {
                        "x": 24.32390642648906,
                        "y": 30.72972485468158,
                        "l": "兄消える"
                    },
                    {
                        "x": 28.42644519146807,
                        "y": 24.906259355701685,
                        "l": "ドント・ウォーリー"
                    },
                    {
                        "x": 27.363007794604584,
                        "y": 16.875114217776634,
                        "l": "カメラを止めるな！"
                    },
                    {
                        "x": 19.31680036717422,
                        "y": 24.547725796177367,
                        "l": "いつのまにか、ここにいる Documentary of 乃木坂46"
                    },
                    {
                        "x": 28.75452206656193,
                        "y": 32.33781982972708,
                        "l": "轢き逃げ －最高の最悪な日－"
                    },
                    {
                        "x": 33.34085587490293,
                        "y": 34.423781639844094,
                        "l": "ワイルドライフ"
                    },
                    {
                        "x": 24.28932115342348,
                        "y": 26.138950323946325,
                        "l": "TOURISM"
                    },
                    {
                        "x": 30.409691103560036,
                        "y": 35.28641446438985,
                        "l": "カメラを止めるな！スピンオフ「ハリウッド大作戦！」"
                    },
                    {
                        "x": 35.97119716680057,
                        "y": 33.32568330348271,
                        "l": "エマの瞳"
                    },
                    {
                        "x": 22.572109189571936,
                        "y": 27.31573631766706,
                        "l": "慶州（キョンジュ）　ヒョンとユニ"
                    },
                    {
                        "x": 29.656636984855915,
                        "y": 34.418080050462635,
                        "l": "イングランド・イズ・マイン  モリッシー, はじまりの物語"
                    },
                    {
                        "x": 36.59412893898136,
                        "y": 28.105378674070437,
                        "l": "あの日々の話"
                    },
                    {
                        "x": 28.361879227973297,
                        "y": 33.48724299202974,
                        "l": "デリバリー"
                    },
                    {
                        "x": 31.212534194551754,
                        "y": 25.363963359170757,
                        "l": "イーちゃんの白い杖"
                    },
                    {
                        "x": 34.104500108836405,
                        "y": 34.82211518738943,
                        "l": "青の帰り道"
                    },
                    {
                        "x": 34.30524399424626,
                        "y": 26.25261243853363,
                        "l": "21世紀の女の子"
                    },
                    {
                        "x": 25.304353716781097,
                        "y": 30.197222690958103,
                        "l": "アンダー・ザ・シルバーレイク"
                    },
                    {
                        "x": 28.366037338715067,
                        "y": 27.713489334961118,
                        "l": "スケート・キッチン"
                    },
                    {
                        "x": 35.05803670956625,
                        "y": 29.21028950156061,
                        "l": "顔たち、ところどころ"
                    },
                    {
                        "x": 24.83490169151365,
                        "y": 33.20985156931993,
                        "l": "沈没家族 劇場版"
                    },
                    {
                        "x": 29.579754820222128,
                        "y": 36.010653845828614,
                        "l": "アリータ：バトル・エンジェル"
                    },
                    {
                        "x": 39.781559771750636,
                        "y": 28.954838232074295,
                        "l": "メモリーズ・オブ・サマー"
                    },
                    {
                        "x": 30.45976403545949,
                        "y": 25.626987199048997,
                        "l": "ザ・バニシング-消失-"
                    },
                    {
                        "x": 20.95016498772378,
                        "y": 35.76450855371358,
                        "l": "スリーアウト！ -プレイボール篇-"
                    },
                    {
                        "x": 30.904774844305,
                        "y": 34.18983574448432,
                        "l": "セメントの記憶"
                    },
                    {
                        "x": 30.33888242361712,
                        "y": 26.65260849789519,
                        "l": "ヨーゼフ・ボイスは挑発する"
                    },
                    {
                        "x": 27.98710980360122,
                        "y": 31.36347757872436,
                        "l": "明治東亰恋伽"
                    },
                    {
                        "x": 38.02587290706808,
                        "y": 28.87598442569598,
                        "l": "隣人のゆくえ　あの夏の歌声"
                    },
                    {
                        "x": 27.208727536132415,
                        "y": 29.694080440006616,
                        "l": "この道"
                    },
                    {
                        "x": 29.886999687000436,
                        "y": 38.70275188309827,
                        "l": "ドール・メーカー"
                    },
                    {
                        "x": 29.42858283763294,
                        "y": 35.620621204774025,
                        "l": "コンフィデンスマンJP"
                    },
                    {
                        "x": 38.06069117085268,
                        "y": 31.56725322869736,
                        "l": "ゴジラ キング・オブ・モンスターズ"
                    },
                    {
                        "x": 35.470425602424044,
                        "y": 18.755629959164988,
                        "l": "スパイダーマン：スパイダーバース"
                    },
                    {
                        "x": 33.93374201547705,
                        "y": 27.727949571669917,
                        "l": "99歳　母と暮らせば"
                    },
                    {
                        "x": 30.41080664328248,
                        "y": 31.287191398687987,
                        "l": "映画プリキュア ミラクルユニバース"
                    },
                    {
                        "x": 26.750275852022984,
                        "y": 27.869398569440392,
                        "l": "パージ：エクスペリメント"
                    },
                    {
                        "x": 19.015633178791653,
                        "y": 34.597516847756935,
                        "l": "さよならくちびる"
                    },
                    {
                        "x": 26.70116379770719,
                        "y": 26.919625774524157,
                        "l": "うちの執事が言うことには"
                    },
                    {
                        "x": 30.77061895527139,
                        "y": 30.582407762257677,
                        "l": "天国でまた会おう"
                    },
                    {
                        "x": 26.992148334009013,
                        "y": 28.71692699374787,
                        "l": "芳華-Youth-"
                    },
                    {
                        "x": 34.48158530038707,
                        "y": 35.36438542321537,
                        "l": "探偵なふたり：リターンズ"
                    },
                    {
                        "x": 24.322632116019918,
                        "y": 30.104024397202686,
                        "l": "かぞくわり"
                    },
                    {
                        "x": 32.82917773005221,
                        "y": 29.101797436618114,
                        "l": "2つ目の窓"
                    },
                    {
                        "x": 38.11710749921263,
                        "y": 14.803236748427715,
                        "l": "劇場版 ファイナルファンタジーXIV 光のお父さん"
                    },
                    {
                        "x": 22.754546815974336,
                        "y": 34.93158282540802,
                        "l": "17歳のシンデレラ"
                    },
                    {
                        "x": 31.269107297807686,
                        "y": 24.8782389625908,
                        "l": "ハロウィーン"
                    },
                    {
                        "x": 37.89970009152184,
                        "y": 29.05494805793417,
                        "l": "ある少年の告白"
                    },
                    {
                        "x": 36.83827163864542,
                        "y": 37.54135263967527,
                        "l": "魂のゆくえ"
                    },
                    {
                        "x": 34.262685245515875,
                        "y": 27.37168121986119,
                        "l": "神と共に 第一章：罪と罰"
                    },
                    {
                        "x": 27.74069588661388,
                        "y": 22.753164965972893,
                        "l": "キュクロプス"
                    },
                    {
                        "x": 27.3959050471209,
                        "y": 21.223288086383477,
                        "l": "山懐に抱かれて"
                    },
                    {
                        "x": 34.14061306088399,
                        "y": 23.824025092551757,
                        "l": "乱世備忘 僕らの雨傘運動"
                    },
                    {
                        "x": 41.432257247067746,
                        "y": 31.24974648543112,
                        "l": "クロノス・ジョウンターの伝説"
                    },
                    {
                        "x": 29.961022973383177,
                        "y": 34.867504187721266,
                        "l": "凪待ち"
                    },
                    {
                        "x": 33.6245796671667,
                        "y": 21.93635082629256,
                        "l": "カニバパリ人肉事件 38 年目の真実"
                    },
                    {
                        "x": 34.165590127824025,
                        "y": 39.23168255089103,
                        "l": "星に語りて～Starry Sky～"
                    },
                    {
                        "x": 24.292821432918263,
                        "y": 32.87394146848594,
                        "l": "海獣の子供"
                    },
                    {
                        "x": 32.45910919033725,
                        "y": 25.73049631031852,
                        "l": "Diner ダイナー"
                    },
                    {
                        "x": 34.853066334155116,
                        "y": 37.491814943469535,
                        "l": "ハイドリヒを撃て！「ナチの野獣」暗殺作戦"
                    },
                    {
                        "x": 26.734145093500878,
                        "y": 31.728761609786467,
                        "l": "祈り"
                    },
                    {
                        "x": 45.15234233090392,
                        "y": 46.25970934543273,
                        "l": "バジュランギおじさんと、小さな迷子"
                    },
                    {
                        "x": 27.374315066624614,
                        "y": 36.337133059031785,
                        "l": "夢の音"
                    },
                    {
                        "x": 32.12565146234404,
                        "y": 28.771596285723003,
                        "l": "作兵衛さんと日本を掘る"
                    },
                    {
                        "x": 23.817775817251494,
                        "y": 23.16301404917231,
                        "l": "涙の数だけ笑おうよ 林家かん平奮闘記"
                    },
                    {
                        "x": 26.534937210541464,
                        "y": 27.25875086079423,
                        "l": "ウトヤ島、7月22日"
                    },
                    {
                        "x": 29.838562633676062,
                        "y": 40.085177815459126,
                        "l": "ヤクザと憲法"
                    },
                    {
                        "x": 31.54352955282459,
                        "y": 25.382445564907435,
                        "l": "幸福なラザロ"
                    },
                    {
                        "x": 29.112268059808805,
                        "y": 29.670942703987738,
                        "l": "RBG 最強の85才"
                    },
                    {
                        "x": 35.724030353584475,
                        "y": 37.464054333777064,
                        "l": "イメージの本"
                    },
                    {
                        "x": 33.55571773671718,
                        "y": 27.027701252275907,
                        "l": "劇場版 Fatestay night Heaven's Feel II. lost butterfly"
                    },
                    {
                        "x": 27.52516173564502,
                        "y": 31.126440331330993,
                        "l": "SANJU／サンジュ"
                    },
                    {
                        "x": 25.146251889313813,
                        "y": 31.540953720235606,
                        "l": "ハッピー・デス・デイ"
                    },
                    {
                        "x": 32.83661911276522,
                        "y": 29.33498063836798,
                        "l": "ハウス・ジャック・ビルト"
                    },
                    {
                        "x": 31.271762052969393,
                        "y": 24.006131424731795,
                        "l": "薄暮"
                    },
                    {
                        "x": 32.46608819968641,
                        "y": 24.92372501535707,
                        "l": "アメリカン・アニマルズ"
                    },
                    {
                        "x": 35.02795493473502,
                        "y": 25.181276893723876,
                        "l": "さよなら、退屈なレオニー"
                    },
                    {
                        "x": 25.468767254219394,
                        "y": 32.9911150371709,
                        "l": "グレイテスト・ショーマン"
                    },
                    {
                        "x": 33.60919009049723,
                        "y": 31.25868604009301,
                        "l": "レプリカズ"
                    },
                    {
                        "x": 31.686396466594797,
                        "y": 34.40668613440877,
                        "l": "久高オデッセイ 第三部 風章"
                    },
                    {
                        "x": 28.85801983584779,
                        "y": 25.781886912538553,
                        "l": "家族にサルーテ！イスキア島は大騒動"
                    },
                    {
                        "x": 23.321800832403692,
                        "y": 31.846615836686492,
                        "l": "モリのいる場所"
                    },
                    {
                        "x": 34.07175055005607,
                        "y": 30.93684376596237,
                        "l": "それいけ！アンパンマン　きらめけ！アイスの国のバニラ姫"
                    },
                    {
                        "x": 23.445732646287006,
                        "y": 29.40722973471639,
                        "l": "ゲッベルスと私"
                    },
                    {
                        "x": 28.713656317843157,
                        "y": 27.4168487205736,
                        "l": "スノー・ロワイヤル"
                    },
                    {
                        "x": 34.0447695453358,
                        "y": 26.492624317287827,
                        "l": "柄本家のゴドー"
                    },
                    {
                        "x": 29.19362479910352,
                        "y": 31.60254824153983,
                        "l": "MONGOL800 -message-"
                    },
                    {
                        "x": 34.39374416007294,
                        "y": 35.583135966158636,
                        "l": "アナと世界の終わり"
                    },
                    {
                        "x": 30.642471975459618,
                        "y": 27.474037387796415,
                        "l": "NORINTEN 稲塚権次郎物語"
                    },
                    {
                        "x": 26.11401661175089,
                        "y": 28.838960002160324,
                        "l": "百年の蔵"
                    },
                    {
                        "x": 31.365101966898905,
                        "y": 34.32591321009668,
                        "l": "こはく"
                    },
                    {
                        "x": 27.488441058848064,
                        "y": 22.64972107846718,
                        "l": "ハーツ・ビート・ラウド たびだちのうた"
                    },
                    {
                        "x": 26.762208862910636,
                        "y": 30.797316897334237,
                        "l": "この世界の片隅に"
                    },
                    {
                        "x": 35.829147714470544,
                        "y": 29.404764986180904,
                        "l": "ハッピー・デス・デイ 2U"
                    },
                    {
                        "x": 34.33989592269091,
                        "y": 27.699113996078662,
                        "l": "カスリコ"
                    },
                    {
                        "x": 29.802473044583216,
                        "y": 26.507030116430098,
                        "l": "リービング・アフガニスタン"
                    },
                    {
                        "x": 30.020941991932627,
                        "y": 26.258035589510317,
                        "l": "リトル・フォレスト 春夏秋冬"
                    },
                    {
                        "x": 28.823620081568933,
                        "y": 34.032658020874806,
                        "l": "ここは退屈迎えに来て"
                    },
                    {
                        "x": 32.08929640566168,
                        "y": 40.325265968652516,
                        "l": "漂うがごとく"
                    },
                    {
                        "x": 27.6561631897911,
                        "y": 24.055904525265582,
                        "l": "嵐電"
                    },
                    {
                        "x": 31.3527469407408,
                        "y": 39.18834417039779,
                        "l": "町田くんの世界"
                    },
                    {
                        "x": 28.341267522006344,
                        "y": 26.98552677974257,
                        "l": "陽のあたる町"
                    },
                    {
                        "x": 29.06952680663248,
                        "y": 28.448299680480567,
                        "l": "サマーフィーリング"
                    },
                    {
                        "x": 26.874009041635716,
                        "y": 30.184498876015503,
                        "l": "台北セブンラブ"
                    },
                    {
                        "x": 35.18056423319476,
                        "y": 32.39544795958212,
                        "l": "パリ、嘘つきな恋"
                    },
                    {
                        "x": 28.43230020791941,
                        "y": 24.093286592048976,
                        "l": "ウィーアーリトルゾンビーズ"
                    },
                    {
                        "x": 32.873024513547186,
                        "y": 32.22076028335628,
                        "l": "最果てリストランテ"
                    },
                    {
                        "x": 33.73763000098358,
                        "y": 34.57841583371293,
                        "l": "盆唄"
                    },
                    {
                        "x": 35.079210505471494,
                        "y": 29.199319486393858,
                        "l": "ソード・オブ・レジェンド　古剣奇譚"
                    },
                    {
                        "x": 29.291310296299777,
                        "y": 24.10373780386983,
                        "l": "東京干潟"
                    },
                    {
                        "x": 31.802265927678054,
                        "y": 30.448171763693352,
                        "l": "柴公園"
                    },
                    {
                        "x": 33.92826657509205,
                        "y": 35.362723358598664,
                        "l": "ラストタンゴ・イン・パリ"
                    },
                    {
                        "x": 21.89004868587414,
                        "y": 31.5494736143619,
                        "l": "映画 賭ケグルイ"
                    },
                    {
                        "x": 36.27894496063394,
                        "y": 28.976338636628913,
                        "l": "万歳！ここは愛の道"
                    },
                    {
                        "x": 36.99346707703439,
                        "y": 24.974406277147303,
                        "l": "多十郎殉愛記"
                    },
                    {
                        "x": 26.75345235971848,
                        "y": 30.666098960606053,
                        "l": "女の機嫌の直し方"
                    },
                    {
                        "x": 21.459403487059564,
                        "y": 36.21675362702541,
                        "l": "ピアッシング"
                    },
                    {
                        "x": 24.538308934940545,
                        "y": 37.26124577456884,
                        "l": "ファイティン！"
                    },
                    {
                        "x": 24.67219370500716,
                        "y": 30.121805706348344,
                        "l": "荒野にて"
                    },
                    {
                        "x": 33.509498303729856,
                        "y": 28.973462464769426,
                        "l": "抗い 記録作家 林えいだい"
                    },
                    {
                        "x": 14.60307682112694,
                        "y": 29.982610470147915,
                        "l": "オンネリとアンネリとひみつのさくせん"
                    },
                    {
                        "x": 29.52260828355067,
                        "y": 33.036147970179165,
                        "l": "江ノ島シネマ"
                    },
                    {
                        "x": 42.027195412680456,
                        "y": 18.290032812426183,
                        "l": "青春ブタ野郎はゆめみる少女の夢を見ない"
                    },
                    {
                        "x": 21.166870631403178,
                        "y": 30.659694195158945,
                        "l": "日日是好日"
                    },
                    {
                        "x": 30.368504222849293,
                        "y": 22.05943039950799,
                        "l": "劇場版 トリニティセブン -天空図書館と真紅の魔王-"
                    },
                    {
                        "x": 25.28399670993038,
                        "y": 26.575942098798546,
                        "l": "月夜釜合戦"
                    },
                    {
                        "x": 26.499077176332847,
                        "y": 27.087123857609846,
                        "l": "アマンダと僕"
                    },
                    {
                        "x": 27.344657982253963,
                        "y": 23.064319740818014,
                        "l": "劇場版「王室教師ハイネ」"
                    },
                    {
                        "x": 25.39714892372465,
                        "y": 29.27108557755183,
                        "l": "レディ・プレイヤー1"
                    },
                    {
                        "x": 23.32632036042306,
                        "y": 29.517911225122152,
                        "l": "小さな恋のうた"
                    },
                    {
                        "x": 34.630302848275356,
                        "y": 27.546534367023956,
                        "l": "ねことじいちゃん"
                    },
                    {
                        "x": 27.132447102810175,
                        "y": 22.980231986749217,
                        "l": "やさしい人"
                    },
                    {
                        "x": 36.405095185774,
                        "y": 34.884402590885045,
                        "l": "私の少女時代 Our Times"
                    },
                    {
                        "x": 29.337965308402485,
                        "y": 26.568123168967624,
                        "l": "軍中楽園"
                    },
                    {
                        "x": 29.1884210112048,
                        "y": 29.04094419477147,
                        "l": "ふたりの女王 メアリーとエリザベス"
                    },
                    {
                        "x": 34.33900762770492,
                        "y": 34.97379439337266,
                        "l": "シャルロット すさび"
                    },
                    {
                        "x": 31.797420216818907,
                        "y": 28.116231952257564,
                        "l": "ラ"
                    },
                    {
                        "x": 30.41250189249049,
                        "y": 37.84891160604837,
                        "l": "氷上の王、ジョン・カリー"
                    },
                    {
                        "x": 39.9003584180932,
                        "y": 34.586701341898454,
                        "l": "YUKIGUNI"
                    },
                    {
                        "x": 29.538802421901746,
                        "y": 26.955742645914505,
                        "l": "バイオレンス・ボイジャー"
                    },
                    {
                        "x": 29.937155803091972,
                        "y": 28.03743844465248,
                        "l": "ボヘミアン・ラプソディ"
                    },
                    {
                        "x": 32.72131293967014,
                        "y": 30.288515942637364,
                        "l": "劇場版パタリロ！"
                    },
                    {
                        "x": 28.643513577783327,
                        "y": 28.926593948241667,
                        "l": "僕たちは希望という名の列車に乗った"
                    },
                    {
                        "x": 36.90511293038463,
                        "y": 28.728814573391777,
                        "l": "12か月の未来図"
                    },
                    {
                        "x": 38.11532061083112,
                        "y": 26.058729870166868,
                        "l": "クリムト エゴン・シーレとウィーン黄金時代"
                    },
                    {
                        "x": 23.047498838855333,
                        "y": 23.337249585330483,
                        "l": "ヒトラーVS.ピカソ 奪われた名画のゆくえ"
                    },
                    {
                        "x": 35.58098413992755,
                        "y": 33.216572366649956,
                        "l": "洗骨"
                    },
                    {
                        "x": 29.439018667288675,
                        "y": 24.685153430282615,
                        "l": "ココロ、オドル"
                    },
                    {
                        "x": 31.432441844625032,
                        "y": 24.830470036675223,
                        "l": "Workers 被災地に起つ"
                    },
                    {
                        "x": 26.702377205947567,
                        "y": 27.514248857332746,
                        "l": "天然☆生活"
                    },
                    {
                        "x": 30.140111704750204,
                        "y": 34.23721142554328,
                        "l": "search／サーチ"
                    },
                    {
                        "x": 29.63718131160265,
                        "y": 26.010256728528585,
                        "l": "希望の樹"
                    },
                    {
                        "x": 33.71744069629692,
                        "y": 32.177855886056484,
                        "l": "THE GUILTY／ギルティ"
                    },
                    {
                        "x": 35.63835220746573,
                        "y": 29.52737816852365,
                        "l": "劇場版 Free!-Road to the World-夢"
                    },
                    {
                        "x": 31.391354614211252,
                        "y": 29.733042266170173,
                        "l": "神と共に 第二章：因と縁"
                    },
                    {
                        "x": 23.44868214911272,
                        "y": 32.383102512105395,
                        "l": "風の波紋"
                    },
                    {
                        "x": 29.65755577126275,
                        "y": 25.693414172094844,
                        "l": "オーファンズ・ブルース"
                    },
                    {
                        "x": 30.382836391648336,
                        "y": 34.02626945583573,
                        "l": "泣くな赤鬼"
                    },
                    {
                        "x": 30.611520163685558,
                        "y": 37.4766319939032,
                        "l": "福島は語る"
                    },
                    {
                        "x": 31.203575473974368,
                        "y": 37.05575537784914,
                        "l": "さらば愛しきアウトロー"
                    },
                    {
                        "x": 25.23564605184538,
                        "y": 24.76963980681989,
                        "l": "ペトラは静かに対峙する"
                    },
                    {
                        "x": 22.930720936234525,
                        "y": 31.339793566013647,
                        "l": "コインロッカーの女"
                    },
                    {
                        "x": 36.14343446350783,
                        "y": 22.066244010463954,
                        "l": "あいが、そいで、こい"
                    },
                    {
                        "x": 32.588581786560496,
                        "y": 33.40815331843034,
                        "l": "初恋～お父さん、チビがいなくなりました"
                    },
                    {
                        "x": 31.35234535667297,
                        "y": 29.599613039290986,
                        "l": "誰もがそれを知っている"
                    },
                    {
                        "x": 31.46297032714644,
                        "y": 34.76014859843841,
                        "l": "ばあばは、だいじょうぶ"
                    },
                    {
                        "x": 32.578825020554525,
                        "y": 31.947031625520488,
                        "l": "LUPIN THE ⅢRD 峰不二子の嘘"
                    },
                    {
                        "x": 30.205576097773598,
                        "y": 34.43574102761724,
                        "l": "マローボーン家の掟"
                    },
                    {
                        "x": 35.838504173194785,
                        "y": 24.87088886853524,
                        "l": "アンノウン・ソルジャー 英雄なき戦場"
                    },
                    {
                        "x": 26.731777892112294,
                        "y": 26.547614173245847,
                        "l": "君の名前で僕を呼んで"
                    },
                    {
                        "x": 26.90011779857263,
                        "y": 31.866949044695197,
                        "l": "映画 としまえん"
                    },
                    {
                        "x": 24.06645191689278,
                        "y": 30.174009627225026,
                        "l": "サスペリア"
                    },
                    {
                        "x": 28.82348690249485,
                        "y": 28.910456853406085,
                        "l": "KING OF PRISM -Shiny Seven Stars- I プロローグ×ユキノジョウ×タイガ"
                    },
                    {
                        "x": 26.956940020727647,
                        "y": 35.918774243629926,
                        "l": "空母いぶき"
                    },
                    {
                        "x": 33.067472770127125,
                        "y": 30.922241353492783,
                        "l": "シンク・オア・スイム　イチかバチか俺たちの夢"
                    },
                    {
                        "x": 35.646535990588994,
                        "y": 32.47680716818956,
                        "l": "フレームアームズ・ガール～きゃっきゃうふふなワンダーランド"
                    },
                    {
                        "x": 33.67556302928297,
                        "y": 23.181525002769572,
                        "l": "ある町の高い煙突"
                    },
                    {
                        "x": 27.722352837190634,
                        "y": 32.851870488609684,
                        "l": "ハンターキラー 潜航せよ"
                    },
                    {
                        "x": 28.917633739841264,
                        "y": 37.372968188211836,
                        "l": "Fatekaleid liner Prisma☆Illya プリズマ☆ファンタズム"
                    },
                    {
                        "x": 24.4097578973783,
                        "y": 30.893289831373597,
                        "l": "ゴールデン・リバー"
                    },
                    {
                        "x": 28.966786429293315,
                        "y": 28.420397150132956,
                        "l": "ハイ・ライフ"
                    },
                    {
                        "x": 37.48973665498286,
                        "y": 24.895648237034408,
                        "l": "無双の鉄拳"
                    },
                    {
                        "x": 21.919697379063372,
                        "y": 33.77573247501224,
                        "l": "田園の守り人たち"
                    },
                    {
                        "x": 31.2163645120325,
                        "y": 29.857601161313642,
                        "l": "ビューティフル・ボーイ"
                    },
                    {
                        "x": 12.721114867719582,
                        "y": 27.650284635535602,
                        "l": "三人の夫"
                    },
                    {
                        "x": 29.6941310562983,
                        "y": 31.718575633346912,
                        "l": "貞子"
                    },
                    {
                        "x": 35.310750894651875,
                        "y": 29.816533499431728,
                        "l": "ガールズ＆パンツァー 最終章 第2話"
                    },
                    {
                        "x": 37.42937641820876,
                        "y": 24.471280528239973,
                        "l": "リヴァプール、最後の恋"
                    },
                    {
                        "x": 31.804851523950415,
                        "y": 26.76659636788465,
                        "l": "センコロール コネクト"
                    },
                    {
                        "x": 25.891387159998732,
                        "y": 29.105134586374312,
                        "l": "劇場版 誰ガ為のアルケミスト"
                    },
                    {
                        "x": 30.77227110307581,
                        "y": 16.599625592384506,
                        "l": "コレット"
                    },
                    {
                        "x": 27.812958478017134,
                        "y": 33.74554431196499,
                        "l": "熱狂宣言"
                    },
                    {
                        "x": 37.24050896605065,
                        "y": 28.880856502008104,
                        "l": "がんと生きる言葉の処方箋"
                    },
                    {
                        "x": 19.3595765234447,
                        "y": 28.528004370804393,
                        "l": "劇場版 響け！ユーフォニアム～誓いのフィナーレ～"
                    },
                    {
                        "x": 27.15142740099996,
                        "y": 35.664054668622995,
                        "l": "ベトナムを懐う"
                    },
                    {
                        "x": 29.961331124764808,
                        "y": 29.454258998917744,
                        "l": "耳を腐らせるほどの愛"
                    },
                    {
                        "x": 26.64544207864602,
                        "y": 30.661133597575304,
                        "l": "劇場版『えいがのおそ松さん』"
                    },
                    {
                        "x": 37.417537213807684,
                        "y": 34.86472831805263,
                        "l": "アイアン・スカイ／第三帝国の逆襲"
                    },
                    {
                        "x": 28.432326619984856,
                        "y": 31.179225698079645,
                        "l": "エリカ38"
                    },
                    {
                        "x": 33.059943867355194,
                        "y": 29.6132787304412,
                        "l": "映画 きかんしゃトーマス Go！Go！地球まるごとアドベンチャー"
                    },
                    {
                        "x": 36.153589953387794,
                        "y": 27.661015193802868,
                        "l": "いちごの唄"
                    },
                    {
                        "x": 30.882947104001058,
                        "y": 39.66613000809432,
                        "l": "勝手にふるえてろ"
                    },
                    {
                        "x": 27.496613521958935,
                        "y": 36.225195808044546,
                        "l": "長いお別れ"
                    },
                    {
                        "x": 30.61727782938189,
                        "y": 37.16400646903347,
                        "l": "新聞記者"
                    },
                    {
                        "x": 34.202894548903295,
                        "y": 20.58872541397153,
                        "l": "あの頃、君を追いかけた"
                    },
                    {
                        "x": 26.74631678816826,
                        "y": 21.47408370450176,
                        "l": "家族のレシピ"
                    },
                    {
                        "x": 37.26387267971728,
                        "y": 28.110706673893976,
                        "l": "誰がために憲法はある"
                    },
                    {
                        "x": 38.06641726271058,
                        "y": 31.368809488526743,
                        "l": "愛がなんだ"
                    },
                    {
                        "x": 26.373582291265645,
                        "y": 34.044704407515226,
                        "l": "ワイルド・レース"
                    },
                    {
                        "x": 29.605071764375687,
                        "y": 22.926330135573455,
                        "l": "バイス"
                    },
                    {
                        "x": 36.18523395207399,
                        "y": 32.26128420657234,
                        "l": "悪霊館"
                    },
                    {
                        "x": 25.61191724790494,
                        "y": 27.500490554856743,
                        "l": "記者たち～衝撃と畏怖の真実～"
                    },
                    {
                        "x": 26.578722856495848,
                        "y": 22.088794953703943,
                        "l": "ホワイト・クロウ 伝説のダンサー"
                    },
                    {
                        "x": 30.11265422816005,
                        "y": 31.876819122121997,
                        "l": "ソローキンの見た桜"
                    },
                    {
                        "x": 35.96263765406528,
                        "y": 25.025773439510534,
                        "l": "ベン・イズ・バック"
                    },
                    {
                        "x": 37.46542479928472,
                        "y": 23.30735768210863,
                        "l": "ガチ星"
                    },
                    {
                        "x": 21.227409010987895,
                        "y": 25.30314908531442,
                        "l": "七つの会議"
                    },
                    {
                        "x": 28.361232362465845,
                        "y": 31.138988395269084,
                        "l": "Tribe Called Discord：Documentary of GEZAN"
                    },
                    {
                        "x": 25.75632685051102,
                        "y": 29.042662152469074,
                        "l": "希望の灯り"
                    },
                    {
                        "x": 29.062470393081455,
                        "y": 36.45554209568938,
                        "l": "シンプル・フェイバー"
                    },
                    {
                        "x": 26.615519860515874,
                        "y": 28.37398056512871,
                        "l": "アラジン"
                    },
                    {
                        "x": 24.76819526331448,
                        "y": 29.64292767058441,
                        "l": "トイ・ストーリー４"
                    },
                    {
                        "x": 24.451201854519482,
                        "y": 22.95654596912175,
                        "l": "GF*BF"
                    },
                    {
                        "x": 23.407860622648112,
                        "y": 30.312263317425103,
                        "l": "パドマーワト 女神の誕生"
                    },
                    {
                        "x": 24.21856509777113,
                        "y": 23.096711261944748,
                        "l": "パピヨン"
                    },
                    {
                        "x": 25.50559724282498,
                        "y": 25.644077492862827,
                        "l": "まく子"
                    },
                    {
                        "x": 31.629034661931676,
                        "y": 21.26177112358239,
                        "l": "ピア まちをつなぐもの"
                    },
                    {
                        "x": 34.09819422250538,
                        "y": 21.130170282536433,
                        "l": "パリの家族たち"
                    },
                    {
                        "x": 33.196769730189125,
                        "y": 35.638679868063605,
                        "l": "仲代達矢 役者を生きる"
                    },
                    {
                        "x": 37.903133783358726,
                        "y": 34.51836986247677,
                        "l": "映画クレヨンしんちゃん 新婚旅行ハリケーン ～失われたひろし～"
                    },
                    {
                        "x": 30.642218765580004,
                        "y": 36.167550267153395,
                        "l": "ダーティ・ガイズ　パリ風俗街潜入捜査線"
                    },
                    {
                        "x": 27.961145379881494,
                        "y": 33.218730490601374,
                        "l": "アガサ・クリスティー ねじれた家"
                    },
                    {
                        "x": 33.049484081667494,
                        "y": 24.968289181147142,
                        "l": "マスカレード・ホテル"
                    },
                    {
                        "x": 27.204907170724066,
                        "y": 28.900626370271688,
                        "l": "名探偵コナン 紺青の拳"
                    },
                    {
                        "x": 19.435369455713825,
                        "y": 35.238130701191544,
                        "l": "ライフ・オン・ザ・ロングボード ２nd Wave"
                    },
                    {
                        "x": 24.68129440215956,
                        "y": 23.02242414036079,
                        "l": "ひいくんのあるく町"
                    },
                    {
                        "x": 31.30529164951144,
                        "y": 31.551146887215246,
                        "l": "パパは奮闘中！"
                    },
                    {
                        "x": 34.130677504454724,
                        "y": 24.221170651772873,
                        "l": "翔んで埼玉"
                    },
                    {
                        "x": 26.830959818805454,
                        "y": 23.758920818004086,
                        "l": "岬の兄妹"
                    },
                    {
                        "x": 26.009910632906,
                        "y": 33.660534237634494,
                        "l": "ザ・フォーリナー／復讐者"
                    },
                    {
                        "x": 29.441253638278077,
                        "y": 24.839704821438488,
                        "l": "ニューヨーク公共図書館 エクス・リブリス"
                    },
                    {
                        "x": 34.442479808373974,
                        "y": 26.451550326932573,
                        "l": "トゥレップ〜「海獣の子供」を探して〜"
                    },
                    {
                        "x": 30.430474736977967,
                        "y": 30.672108855910835,
                        "l": "ニッポニアニッポン フクシマ狂詩曲"
                    },
                    {
                        "x": 35.05607360110528,
                        "y": 15.03310418372999,
                        "l": "ダヤンとタマと飛び猫と 3つの猫の物語"
                    },
                    {
                        "x": 29.314431426722063,
                        "y": 29.840359081988293,
                        "l": "グリーンブック"
                    },
                    {
                        "x": 26.604530943928552,
                        "y": 37.65287421710566,
                        "l": "きみと、波にのれたら"
                    },
                    {
                        "x": 34.38847309540688,
                        "y": 32.59547600098864,
                        "l": "武蔵－むさし－"
                    },
                    {
                        "x": 36.569908345337154,
                        "y": 30.941976915949244,
                        "l": "ニューヨーク 最高の訳あり物件"
                    },
                    {
                        "x": 31.291592453264737,
                        "y": 32.598464109962265,
                        "l": "ジョナサン　ふたつの顔の男"
                    },
                    {
                        "x": 29.257086220132535,
                        "y": 33.97112694004948,
                        "l": "オーヴァーロード"
                    },
                    {
                        "x": 25.63861421591524,
                        "y": 33.85902296755585,
                        "l": "名探偵ピカチュウ"
                    },
                    {
                        "x": 33.11108147803148,
                        "y": 34.09433208204545,
                        "l": "マイ・ブックショップ"
                    },
                    {
                        "x": 30.082052152834525,
                        "y": 26.524499857146303,
                        "l": "歎異抄をひらく"
                    },
                    {
                        "x": 25.167068652829435,
                        "y": 32.057040474479265,
                        "l": "ザ・ファブル"
                    },
                    {
                        "x": 32.33354772997735,
                        "y": 17.57094135664501,
                        "l": "ガーデンアパート"
                    },
                    {
                        "x": 32.17902615024552,
                        "y": 35.451861300682395,
                        "l": "ガルヴェストン"
                    },
                    {
                        "x": 37.44429627796803,
                        "y": 24.528276067735018,
                        "l": "キラーズ・セッション"
                    },
                    {
                        "x": 32.64654027946186,
                        "y": 30.682543995235463,
                        "l": "ホットギミック ガールミーツボーイ"
                    },
                    {
                        "x": 29.17229447608188,
                        "y": 33.00602718251703,
                        "l": "チア男子!!"
                    },
                    {
                        "x": 28.778837404905328,
                        "y": 23.025130315584253,
                        "l": "シード ～生命の糧～"
                    },
                    {
                        "x": 30.893238180501374,
                        "y": 34.64937622974716,
                        "l": "クローゼットに閉じこめられた僕の奇想天外な旅"
                    },
                    {
                        "x": 32.51599474858717,
                        "y": 31.884949979271322,
                        "l": "キングダム"
                    },
                    {
                        "x": 22.153112126073808,
                        "y": 24.389362290731704,
                        "l": "旅のおわり世界のはじまり"
                    },
                    {
                        "x": 27.6029673094629,
                        "y": 29.206039694079227,
                        "l": "僕たちのラストステージ"
                    },
                    {
                        "x": 20.435498660851078,
                        "y": 33.996072128299716,
                        "l": "デッド・ウィッシュ"
                    },
                    {
                        "x": 20.274312325075627,
                        "y": 35.39728011756305,
                        "l": "タレンタイム〜優しい歌"
                    },
                    {
                        "x": 23.923786708911877,
                        "y": 38.76763471288989,
                        "l": "アレッポ 最後の男たち"
                    },
                    {
                        "x": 30.528543160586292,
                        "y": 21.429101955310948,
                        "l": "蟹の惑星"
                    },
                    {
                        "x": 41.135899304924884,
                        "y": 15.350578156205017,
                        "l": "プロメア"
                    },
                    {
                        "x": 34.06406069036844,
                        "y": 24.714490006948154,
                        "l": "ビリーブ 未来への大逆転"
                    },
                    {
                        "x": 36.79872811408433,
                        "y": 24.667578879206413,
                        "l": "サムライマラソン"
                    },
                    {
                        "x": 30.00681359985644,
                        "y": 30.691342330003643,
                        "l": "ANIARA アニアーラ"
                    },
                    {
                        "x": 42.58474356544947,
                        "y": 34.59358309560914,
                        "l": "劇場版 うたの☆プリンスさまっ♪ マジ LOVE キングダム"
                    },
                    {
                        "x": 29.734833648876503,
                        "y": 28.376372145025908,
                        "l": "リアム16歳、はじめての学校"
                    },
                    {
                        "x": 22.734666874792083,
                        "y": 36.73485082483377,
                        "l": "恐怖の報酬 オリジナル完全版"
                    },
                    {
                        "x": 20.28307375817864,
                        "y": 29.151387772501295,
                        "l": "デッドエンドの思い出"
                    },
                    {
                        "x": 35.21584139778339,
                        "y": 28.47194044125128,
                        "l": "ぼけますから、よろしくお願いします。"
                    },
                    {
                        "x": 26.540911752889176,
                        "y": 25.612331375256815,
                        "l": "老人ファーム"
                    },
                    {
                        "x": 28.85024317103657,
                        "y": 23.93673431206784,
                        "l": "新宿タイガー"
                    },
                    {
                        "x": 28.862607886772228,
                        "y": 24.151745402777973,
                        "l": "ビル・エヴァンス タイム・リメンバード"
                    },
                    {
                        "x": 24.98430016155648,
                        "y": 34.280316154929054,
                        "l": "運び屋"
                    },
                    {
                        "x": 38.14059559433874,
                        "y": 26.32350209658641,
                        "l": "月極オトコトモダチ"
                    },
                    {
                        "x": 39.16744626368037,
                        "y": 18.245741568234763,
                        "l": "ちえりとチェリー"
                    },
                    {
                        "x": 27.38471475114787,
                        "y": 32.9873756852163,
                        "l": "ずぶぬれて犬ころ"
                    },
                    {
                        "x": 25.103007970177075,
                        "y": 23.445890959884025,
                        "l": "メン・イン・ブラック：インターナショナル"
                    },
                    {
                        "x": 26.792433287986356,
                        "y": 23.892949554081138,
                        "l": "蹴る"
                    },
                    {
                        "x": 24.281081400840332,
                        "y": 35.24208523366831,
                        "l": "赤い雪 Red Snow"
                    },
                    {
                        "x": 33.04552790427895,
                        "y": 39.35621448685543,
                        "l": "あの日のオルガン"
                    },
                    {
                        "x": 29.54123130013636,
                        "y": 23.77919105067683,
                        "l": "桐島、部活やめるってよ"
                    },
                    {
                        "x": 19.063840976186455,
                        "y": 35.54051866345605,
                        "l": "映画しまじろう　しまじろうとうるるのヒーローランド"
                    },
                    {
                        "x": 28.137333072549648,
                        "y": 37.99571154611596,
                        "l": "二十歳"
                    },
                    {
                        "x": 32.069201797743176,
                        "y": 23.015092282267457,
                        "l": "今日も嫌がらせ弁当"
                    },
                    {
                        "x": 35.575414867871245,
                        "y": 28.891509937963775,
                        "l": "GOZEN 純恋の剣"
                    },
                    {
                        "x": 26.235655118506283,
                        "y": 34.59378176956106,
                        "l": "HOMIE KEI チカーノになった日本人"
                    },
                    {
                        "x": 26.063093486886196,
                        "y": 26.030088161900686,
                        "l": "ビール・ストリートの恋人たち"
                    },
                    {
                        "x": 19.41391516290997,
                        "y": 28.191592451146324,
                        "l": "僕はイエス様が嫌い"
                    },
                    {
                        "x": 33.51433752248186,
                        "y": 23.03608339291403,
                        "l": "シスターフッド"
                    },
                    {
                        "x": 29.42803605907244,
                        "y": 23.19022367833766,
                        "l": "The Crossing -ザ・クロッシング- PartⅠ"
                    },
                    {
                        "x": 29.459046121409166,
                        "y": 30.293208128661032,
                        "l": "COLD WAR　あの歌、２つの心"
                    },
                    {
                        "x": 36.26478307459522,
                        "y": 39.56624535013572,
                        "l": "ロミオとジュリエット"
                    },
                    {
                        "x": 27.43508211935248,
                        "y": 33.44472127961533,
                        "l": "ハッパGoGo 大統領極秘指令"
                    },
                    {
                        "x": 34.37574561845777,
                        "y": 20.639220424827347,
                        "l": "X-MEN:ダーク・フェニックス"
                    },
                    {
                        "x": 28.51956773378937,
                        "y": 22.39829514468104,
                        "l": "マックイーン:モードの反逆児"
                    },
                    {
                        "x": 27.27635554073693,
                        "y": 38.26993862865579,
                        "l": "The Crossing -ザ・クロッシング- PartⅡ"
                    },
                    {
                        "x": 26.246460246863986,
                        "y": 24.92699545305846,
                        "l": "バックトレース"
                    },
                    {
                        "x": 32.84177284438301,
                        "y": 32.42933834427377,
                        "l": "雪子さんの足音"
                    },
                    {
                        "x": 35.607075017060616,
                        "y": 25.74085912222467,
                        "l": "万引き家族"
                    },
                    {
                        "x": 39.797062864825065,
                        "y": 37.975096353037095,
                        "l": "疑惑とダンス"
                    },
                    {
                        "x": 37.09632427547158,
                        "y": 33.72680846983945,
                        "l": "ヒトラーを欺いた黄色い星"
                    },
                    {
                        "x": 33.66266172322215,
                        "y": 27.59305040543137,
                        "l": "安市城 グレート・バトル"
                    },
                    {
                        "x": 22.801770524250166,
                        "y": 25.936226424595702,
                        "l": "家へ帰ろう"
                    }
                ]
            }
        ]
    }
}